odoo/addons/pos_payment_terminal/README.rst
odoo/addons/pos_payment_terminal/__init__.py
odoo/addons/pos_payment_terminal/__manifest__.py
odoo/addons/pos_payment_terminal/i18n/es.po
odoo/addons/pos_payment_terminal/i18n/fr.po
odoo/addons/pos_payment_terminal/i18n/hr_HR.po
odoo/addons/pos_payment_terminal/i18n/it.po
odoo/addons/pos_payment_terminal/i18n/nl_NL.po
odoo/addons/pos_payment_terminal/i18n/pos_payment_terminal.pot
odoo/addons/pos_payment_terminal/models/__init__.py
odoo/addons/pos_payment_terminal/models/pos_payment_method.py
odoo/addons/pos_payment_terminal/readme/CONFIGURE.rst
odoo/addons/pos_payment_terminal/readme/CONTRIBUTORS.rst
odoo/addons/pos_payment_terminal/readme/DESCRIPTION.rst
odoo/addons/pos_payment_terminal/readme/INSTALL.rst
odoo/addons/pos_payment_terminal/readme/USAGE.rst
odoo/addons/pos_payment_terminal/static/description/icon.png
odoo/addons/pos_payment_terminal/static/description/index.html
odoo/addons/pos_payment_terminal/static/description/pos_payment_method_form.png
odoo/addons/pos_payment_terminal/static/src/js/models.js
odoo/addons/pos_payment_terminal/static/src/js/payment_terminal.js
odoo/addons/pos_payment_terminal/views/assets.xml
odoo/addons/pos_payment_terminal/views/pos_payment_method.xml
odoo13_addon_pos_payment_terminal-13.0.1.1.0.dist-info/METADATA
odoo13_addon_pos_payment_terminal-13.0.1.1.0.dist-info/WHEEL
odoo13_addon_pos_payment_terminal-13.0.1.1.0.dist-info/top_level.txt
odoo13_addon_pos_payment_terminal-13.0.1.1.0.dist-info/RECORD
